{
  "key": "a66fb46feabe614085b5e7889dc6650b",
  "value": [
    {
      "rule": "C003",
      "line": 6,
      "column": 0,
      "severity": "warning",
      "message": "Variable name 'API_DELAY_MS' uses an uncommon abbreviation 'MS' for milliseconds.",
      "suggestion": "Rename 'API_DELAY_MS' to 'API_DELAY_MILLISECONDS' for clarity.",
      "codeSnippet": "ERROR_CREATE_REVIEW,",
      "filePath": "d:\\intern sun\\PR1\\naitei14_fe_nhom2\\src\\apis\\reviews\\index.ts",
      "category": "code_quality",
      "categoryName": "Code Quality",
      "analysisMode": "medium",
      "confidence": 0.85
    },
    {
      "rule": "C003",
      "line": 9,
      "column": 0,
      "severity": "warning",
      "message": "Variable name 'ms' uses a single-character abbreviation for milliseconds.",
      "suggestion": "Rename 'ms' to 'milliseconds' for clarity.",
      "codeSnippet": "",
      "filePath": "d:\\intern sun\\PR1\\naitei14_fe_nhom2\\src\\apis\\reviews\\index.ts",
      "category": "code_quality",
      "categoryName": "Code Quality",
      "analysisMode": "medium",
      "confidence": 0.85
    },
    {
      "rule": "S001",
      "line": 48,
      "column": 0,
      "severity": "warning",
      "message": "Access control error in hasUserReviewedProduct: returns false on fetch error, potentially leaking existence information or failing insecurely.",
      "suggestion": "Throw an error or deny access explicitly instead of returning false when response is not ok.",
      "codeSnippet": "method: 'POST',",
      "filePath": "d:\\intern sun\\PR1\\naitei14_fe_nhom2\\src\\apis\\reviews\\index.ts",
      "category": "security",
      "categoryName": "Security",
      "analysisMode": "medium",
      "confidence": 0.85
    },
    {
      "rule": "S002",
      "line": 14,
      "column": 0,
      "severity": "warning",
      "message": "getReviewsByProductId relies on productId from client without verifying ownership or authorization.",
      "suggestion": "Add backend-side authorization to ensure the requesting user is allowed to access reviews for the given productId.",
      "codeSnippet": "window.setTimeout(() => {",
      "filePath": "d:\\intern sun\\PR1\\naitei14_fe_nhom2\\src\\apis\\reviews\\index.ts",
      "category": "security",
      "categoryName": "Security",
      "analysisMode": "medium",
      "confidence": 0.85
    },
    {
      "rule": "S002",
      "line": 37,
      "column": 0,
      "severity": "warning",
      "message": "createReview does not verify resource ownership or authorization for review creation.",
      "suggestion": "Ensure backend validates that the user is authorized to create a review for the specified product.",
      "codeSnippet": "export const createReview = async (review: Omit<ProductReview, 'id' | 'date' | 'createdAt'>): Promise<ProductReview> => {",
      "filePath": "d:\\intern sun\\PR1\\naitei14_fe_nhom2\\src\\apis\\reviews\\index.ts",
      "category": "security",
      "categoryName": "Security",
      "analysisMode": "medium",
      "confidence": 0.85
    },
    {
      "rule": "S002",
      "line": 48,
      "column": 0,
      "severity": "warning",
      "message": "hasUserReviewedProduct uses userId and productId from client without verifying ownership or authorization.",
      "suggestion": "Implement backend-side checks to confirm the user is authorized to query reviews for the given productId.",
      "codeSnippet": "method: 'POST',",
      "filePath": "d:\\intern sun\\PR1\\naitei14_fe_nhom2\\src\\apis\\reviews\\index.ts",
      "category": "security",
      "categoryName": "Security",
      "analysisMode": "medium",
      "confidence": 0.85
    }
  ],
  "timestamp": 1765343413416,
  "version": "1.0.0",
  "fileHash": ""
}